sample/__init__.py
sample/main.py
sample/main_dml.py
sample/main_wait.py
sample/workers_test.py
sample/sample_worker_module/__init__.py
sample/sample_worker_module/worker1.py
sample/sample_worker_module/worker_module_2/__init__.py
sample/sample_worker_module/worker_module_2/worker2.py
unmeshed/__init__.py
unmeshed/sdk/__init__.py
unmeshed/sdk/logger_config.py
unmeshed/sdk/unmeshed_client.py
unmeshed/sdk/apis/__init__.py
unmeshed/sdk/apis/file_management/__init__.py
unmeshed/sdk/apis/file_management/file_management_client.py
unmeshed/sdk/apis/http/__init__.py
unmeshed/sdk/apis/http/http_client_factory.py
unmeshed/sdk/apis/http/http_request_factory.py
unmeshed/sdk/apis/poller/__init__.py
unmeshed/sdk/apis/poller/poller_client.py
unmeshed/sdk/apis/poller/work_result.py
unmeshed/sdk/apis/process/__init__.py
unmeshed/sdk/apis/process/process_client.py
unmeshed/sdk/apis/registration/__init__.py
unmeshed/sdk/apis/registration/registration_client.py
unmeshed/sdk/apis/steps/__init__.py
unmeshed/sdk/apis/steps/steps_client.py
unmeshed/sdk/apis/submit/__init__.py
unmeshed/sdk/apis/submit/submit_client.py
unmeshed/sdk/apis/submit/work_response_builder.py
unmeshed/sdk/apis/workers/__init__.py
unmeshed/sdk/apis/workers/worker.py
unmeshed/sdk/common/__init__.py
unmeshed/sdk/common/api_call_type.py
unmeshed/sdk/common/client_submit_result.py
unmeshed/sdk/common/delete_file_request.py
unmeshed/sdk/common/delete_file_response.py
unmeshed/sdk/common/download_file_base64_response.py
unmeshed/sdk/common/download_file_request.py
unmeshed/sdk/common/file_entry.py
unmeshed/sdk/common/json_decorator.py
unmeshed/sdk/common/list_files_request.py
unmeshed/sdk/common/list_files_response.py
unmeshed/sdk/common/poll_request_data.py
unmeshed/sdk/common/process_action_response_data.py
unmeshed/sdk/common/process_configuration.py
unmeshed/sdk/common/process_data.py
unmeshed/sdk/common/process_definition.py
unmeshed/sdk/common/process_request_data.py
unmeshed/sdk/common/process_search_request.py
unmeshed_sdk-1.3.0.dist-info/licenses/LICENSE
unmeshed_sdk-1.3.0.dist-info/METADATA
unmeshed_sdk-1.3.0.dist-info/WHEEL
unmeshed_sdk-1.3.0.dist-info/top_level.txt
unmeshed_sdk-1.3.0.dist-info/RECORD
