Metadata-Version: 2.4
Name: unmeshed-sdk
Version: 1.3.0
Summary: Python SDK for Unmeshed Orchestration platform
Home-page: https://github.com/stablequark/unmeshed-python-sdk
Author: Unmeshed
Author-email: pippython@unmeshed.com
Classifier: Intended Audience :: Developers
Classifier: Intended Audience :: System Administrators
Classifier: Operating System :: OS Independent
Classifier: Programming Language :: Python :: 3
Classifier: Topic :: Software Development :: Libraries :: Python Modules
Requires-Python: >=3.5
License-File: LICENSE
Requires-Dist: requests
Requires-Dist: setuptools
Requires-Dist: pytest
Requires-Dist: numpy
Dynamic: author
Dynamic: author-email
Dynamic: classifier
Dynamic: description
Dynamic: description-content-type
Dynamic: home-page
Dynamic: license-file
Dynamic: requires-dist
Dynamic: requires-python
Dynamic: summary
